setup.py
discord_requests.py.egg-info/PKG-INFO
discord_requests.py.egg-info/SOURCES.txt
discord_requests.py.egg-info/dependency_links.txt
discord_requests.py.egg-info/requires.txt
discord_requests.py.egg-info/top_level.txt
discord_requests_lib/__init__.py